pycron/__init__.py
pycron-3.1.2.dist-info/LICENSE
pycron-3.1.2.dist-info/METADATA
pycron-3.1.2.dist-info/WHEEL
pycron-3.1.2.dist-info/RECORD
