Metadata-Version: 2.3
Name: pycron
Version: 3.1.2
Summary: Simple cron-like parser, which determines if current datetime matches conditions.
License: MIT
Keywords: cron,parser
Author: Kimmo Huoman
Author-email: kipenroskaposti+pycron@gmail.com
Requires-Python: >=3.9,<4.0
Classifier: License :: OSI Approved :: MIT License
Classifier: Programming Language :: Python :: 3
Classifier: Programming Language :: Python :: 3.9
Classifier: Programming Language :: Python :: 3.10
Classifier: Programming Language :: Python :: 3.11
Classifier: Programming Language :: Python :: 3.12
Classifier: Programming Language :: Python :: 3.13
Project-URL: Homepage, https://github.com/kipe/pycron
Project-URL: Repository, https://github.com/kipe/pycron
